{
  "AddressLine1": "Address line 1",
  "AddressLine2": "Address line 2",
  "Adults": "Adults",
  "Amenities": "Amenities",
  "AmountDueToday": "Amount due today",
  "Author": "Author",
  "Availability": "Availability",
  "AvgPricePerNight": "{0} avg/night",
  "BackToListing": "Back to listing...",
  "BackToSearch": "Back to search",
  "BathroomPlural": "{0} bathrooms",
  "BathroomSingular": "1 bathroom",
  "BathroomsTitle": "Bathrooms",
  "BedroomNone": "Studio",
  "BedroomPlural": "{0} bedrooms",
  "BedroomSingular": "1 bedroom",
  "Beds": "Beds",
  "BillingAddress": "Billing address",
  "Book": "Book",
  "Booked": "Booked",
  "Booking": "Booking",
  "BookingCongratulations": "Congratulations, your booking has been confirmed",
  "BookingErrorGeneric": "An Error occured during the booking, please contact our Customer service",
  "BookingErrorRequestTimeout": "Quote request timed out, please contact our Customer service",
  "BookingErrorQuoteFailed": "Quote failed, please contact our Customer service",
  "BookingErrorSalesChannelNull": "Quote failed due to sales channel configuration issue, please contact our Customer service",
  "BookingErrorHttpRequest": "An Error occured while requesting data for booking, please contact our Customer service",
  "BookingItem": "Item",
  "BookNow": "Book now",
  "BookNowForPrice": "Book now for {0}",
  "By": "By",
  "CancellationPolicy": "Cancellation Policy",
  "CancellationPolicyCancelAfter": "if you cancel on or after {0}",
  "CancellationPolicyCancelBefore": "if you cancel before {0}",
  "CancellationPolicyLessThanBeforeCheckIn": "if you cancel {0} or less before check-in",
  "CancellationPolicyMoreThanAfterBookingOrAfter": "if you cancel on or after {0} or more than {1} after booking",
  "CancellationPolicyMoreThanAfterBookingOrLessThanBeforeCheckin": "if you cancel more than {0} after booking or {1} or less before check-in",
  "CancellationPolicyMoreThanBeforeCheckIn": "if you cancel more than {0} before check-in",
  "CancellationPolicyWithinAfterBookingAndBefore": "if you cancel before {0} and are within {1} of booking",
  "CancellationPolicyWithinAfterBookingAndBeforeCheckIn": "if you cancel within {0} of booking and are more than {1} before check-in",
  "CancellationTimelineAfterBooking": "{0} after booking",
  "CancellationTimelineBeforeCheckin": "{0} before check-in",
  "CardDetails": "Card details",
  "Categories": "Categories:",
  "Category": "Category",
  "ChatWithALiveAgent": "Chat with a live agent",
  "CheapestCarRentals": "These just might be\r\nthe cheapest car\r\nrental rates you’ll\r\never find.",
  "CheckIn": "Check-in",
  "CheckInAndCheckOut": "Checkin & Checkout",
  "CheckInDateNotAllowed": "Property is not available for check-in on provided date",
  "CheckInFromTime": "Check-in from {0}",
  "CheckInOutRequiredMessage": "Check-in & check-out is required",
  "CheckOutByTime": "Check-out by {0}",
  "CheckOutDateNotAllowed": "Property is not available for check-out on provided date",
  "Children": "Children",
  "ClearDatesButtonText": "Clear dates",
  "ClearForm": "Clear Form",
  "Close": "Close",
  "Confirm": "Confirm",
  "ConfirmAndPay": "Confirm & Pay",
  "ConfirmYourDetails": "Confirm your details",
  "ConfirmYourStay": "Confirm your stay",
  "Contact": "Contact",
  "ContactBusinessServicesFormHeading": "Contact Business Services",
  "ContactFormTypeGuests": "Guests and Travellers",
  "ContactGuestServicesFormHeading": "Contact Guest Services",
  "ContactUs": "Contact Us",
  "ContactUsSuccess": "Thanks for getting in touch. We will get back to you as soon as possible.",
  "Continue": "Continue",
  "Copyright": "© Copyright 2001 - {0}. All content and rights of this website are copyrighted and reserved.",
  "Country": "Country",
  "CountryFilterTitle": "Where do you want to go?",
  "DateFilterTitlePlaceholder": "Please select your dates",
  "Dates": "Dates",
  "DayCheckIn": "{0} check-in",
  "DayCheckOut": "{0} check-out",
  "DayPlural": "{0} days",
  "DaySingular": "1 day",
  "Description": "Description",
  "DueToday": "Due today",
  "Email": "Email",
  "EmailRequiredMessage": "Email is required",
  "EmailTemplateBusinessContactUs": "LeaveTownBuisnessContactUs",
  "EmailTemplateContactUs": "LeaveTownContactUs",
  "EnterBillingBelowAndConfirm": "Enter your billing details below and confirm your booking today",
  "EnterContactAndBilling": "Please enter your contact & billing details",
  "EnterYourDetails": "Enter your details",
  "ExceedsMaxOccupancy": "Exceeds maximum occupancy",
  "ExceedsMaxPets": "Exceeds maximum number of pets",
  "ExceedsMaxStayNights": "Exceeds maximum length of stay",
  "FeaturedPost": "Featured post",
  "Features": "Features",
  "FeeAutohost": "Autohost Fee",
  "FeeCleaning": "Cleaning Fee",
  "FeeExtraAdult": "Extra Adult Fees",
  "FeeService": "Service Fee",
  "FilterBadge": "{0}: {1}",
  "FindACar": "Find a Car",
  "FirstName": "First name",
  "FirstNameRequiredMessage": "First Name is required",
  "FooterMissionStatement": "",
  "FoundListingCountResults": "Found {0} results",
  "FullRefund": "Free cancellation",
  "GoBackToChangeYourDates": "go back to change your dates and guests",
  "GuestPlural": "{0} guests",
  "GuestSingular": "1 guest",
  "Guests": "Guests",
  "HalfRefund": "50% guest refund",
  "Home": "Home",
  "HourPlural": "{0} hours",
  "HourSingular": "1 hour",
  "In": "in",
  "IndexCounter": "{0} of {1}",
  "Info": "Info",
  "Inquire": "Inquire",
  "InquireOnly": "Inquire only",
  "InquiryMessagePlaceholder": "What would you like to ask?",
  "InvalidCurrency": "Invalid booking currency",
  "InvalidStayDates": "Check-out date must be after check-in date",
  "InvalidPaymentRequest": "Invalid payment request.  Please try again or request a new payment link.",
  "Jetstream": "Jetstream",
  "LastName": "Last name",
  "LastNameRequiredMessage": "Last Name is required",
  "LatestPosts": "Latest posts",
  "ListingCheckInDate": "Check-in from {0}",
  "ListingCheckOutDate": "Check-out by {0}",
  "Location": "Location",
  "LocationOfPortfolio": "Location of porfolio",
  "LoadingPrice": "Loading price...",
  "MakeAnInquiry": "Make an inquiry",
  "MapHide": "Hide map",
  "MapShow": "Show map",
  "Message": "Message",
  "MessageRequiredMessage": "Message is Required",
  "MinAdvancedNoticeNotMet": "Minimum notice before check-in date not met within the resort's local timezone.",
  "MinStayNightsNotMet": "Minimum length of stay not met",
  "MoreFilters": "More Filters",
  "NewsletterSubscribeFailure": "Failed to subscribe to the newsletter. Please contact support to continue the subscription process.",
  "NewsletterSubscribeSuccessful": "Thank you for subscribing to our newsletter. Please check your emails!",
  "Next": "Next",
  "NextPosts": "Next Posts",
  "NoRefund": "No refund",
  "NoResults": "No matching results found",
  "NotAvailable": "Property is not available for one or more nights",
  "NotPetFriendly": "Property is not pet friendly",
  "NumberOfAdultsMessage": "Please enter a value greater than 0 and less than 100",
  "NumberOfAdultsPlural": "{0} adults",
  "NumberOfAdultsSingular": "{0} adult",
  "NumberOfBedrooms": "Bedrooms",
  "NumberOfChildrenPlural": "{0} children",
  "NumberOfChildrenSingular": "{0} child",
  "NumberOfNights": "{0} nights",
  "NumberOfNightsInLocation": "{0} nights in {1}",
  "NumberOfPetsPlural": "{0} pets",
  "NumberOfPetsSingular": "{0} pet",
  "NumberOfProperties": "Number of properties",
  "NumberOfPropertiesMessage": "Please enter a value greater than 0",
  "On": "on",
  "Other": "Other",
  "Page": "page",
  "PaymentHasBeenTaken": "Payment has been taken and your booking has been confirmed",
  "PaymentPageTitle": "Guest Payment",
  "PaymentPageGenericError": "This payment has already been completed or an error has occurred.  If necessary, please contact the host to request another payment link.",
  "PaymentThankYouPageTitle": "Thank you for your payment",
  "PaymentThankYouEnjoyYourStay": "We hope you enjoy your stay",
  "PetFees": "Pet Fees",
  "PetPlural": "{0} pets",
  "PetSingular": "1 pet",
  "Pets": "Pets",
  "Phone": "Phone",
  "PhoneIncludingExtenstion": "Phone (inc. extension)",
  "PhoneRequiredMessage": "Phone is required",
  "PleaseConfirmYourDetails": "Please confirm your details",
  "PleasePay": "Please pay",
  "Previous": "Previous",
  "PreviousPosts": "Previous Posts",
  "Price": "Price",
  "PricingTooltip": "Amount quoted is for cost of stay excluding fees and taxes.  Final price available on property page.",
  "Privacy": "Privacy",
  "PrivacyPolicy": "Privacy Policy",
  "Promotion": "Promotion",
  "PropertyAcceptsPayments": "This property accepts payments in {0}. We will transact this payment due today as {1}",
  "PropertyTypes": "Property types",
  "Published": "Published",
  "Quantity": "Quantity",
  "ReadMore": "Read more",
  "ReceiveDiscountsAndPromotionsInbox": "Receive discounts\r\n& promotions in\r\nyour inbox. 100%\r\nspam free.",
  "ReservationRef": "Reservation ref: #{0}",
  "ReviewYourGuests": "Review your guests",
  "ReviewYourOrderDetails": "Review your order details",
  "ReviewYourStay": "Review your stay",
  "RoomsAndBeds": "Rooms & Beds",
  "SaveAndClose": "Save & close",
  "Search": "Search",
  "SeeForYourself": "Yep, we just checked. See for yourself.",
  "SelectDates": "Select dates",
  "SelectYourCheckInDate": "Select your check-in day",
  "SelectYourCheckOutDate": "Select your check-out day",
  "SelectYourDates": "Select your dates",
  "SelectYourGuests": "Select your guests",
  "SendInquiry": "Send Inquiry",
  "SendingBusyMessage": "Sending ...",
  "ServiceFees": "Service Fees",
  "ShowLessButtonText": "Show less",
  "ShowMoreButtonText": "Show more",
  "SortAscending": "(Low → High)",
  "SortBy": "Sort by",
  "SortDescending": "(High → Low)",
  "SortOptionPrice": "Price",
  "SortOptionRecentlyAdded": "Recently Added",
  "SortOptionRelevance": "Relevance",
  "SortOptionSleeps": "Sleeps",
  "StateCounty": "State / county",
  "StripePaymentCancelledHeading": "Payment cancelled",
  "StripePaymentCancelledMessage": "Your payment was cancelled",
  "StripePaymentSuccessfulHeading": "Payment successful",
  "StripePaymentSuccessfulMessage": "Your payment was successful",
  "Subscribe": "Subscribe",
  "SubscribeToOurNewsletter": "Subscribe to our newsletter",
  "Suitability": "Suitability",
  "TaxesAndFees": "Taxes & Fees at {0}%",
  "TechnicalError": "Unexpected technical error",
  "TermsAndConditions": "Terms & Conditions",
  "TermsAndConditionsCheckText": "I agree to the",
  "ThankYouForBookingWithUs": "You will receive an email confirmation with all the details of your booking. Thank you for booking with us!",
  "Total": "Total",
  "TotalPrice": "Total price",
  "TownCity": "Town / city",
  "TypeOfBusiness": "Type of business",
  "Uncategorized": "Uncategorized",
  "UseDifferentBillingAddress": "Use different billing address",
  "UseSameAddress": "Use same address",
  "ValidEmailMessage": "Please enter a valid email",
  "ValidUrlMessage": "Please enter a valid url",
  "View": "View",
  "ViewGalleryButtonText": "View Gallery ({0} photos)",
  "Website": "Website",
  "WebsiteNotValidMessage": "Please enter a valid url",
  "WebsiteRequiredMessage": "Website is required",
  "YourContactDetails": "Your contact details",
  "YourDetails": "Your details",
  "YourParty": "Your party: {0}",
  "ZipPostalCode": "Zip / postal code"
}